wyra/__init__.py
wyra/crypto.py
wyra/data_maker.py
wyra-0.0.6.dist-info/METADATA
wyra-0.0.6.dist-info/WHEEL
wyra-0.0.6.dist-info/licenses/LICENSE
wyra-0.0.6.dist-info/RECORD
