Metadata-Version: 2.4
Name: wyra
Version: 0.0.6
Summary: Fine Tuning Data Maker
Project-URL: Homepage, https://github.com/sauloleite/wyra
Project-URL: Issues, https://github.com/sauloleite/wyra/issues
Author-email: Saulo Leite <sjoldeveloper@gmail.com>
License-File: LICENSE
Classifier: License :: OSI Approved :: MIT License
Classifier: Operating System :: OS Independent
Classifier: Programming Language :: Python :: 3
Requires-Python: >=3.10
Requires-Dist: cryptography
Requires-Dist: google-genai
Requires-Dist: json-repair
Requires-Dist: openai
Requires-Dist: tiktoken
